jetkmail/__init__.py
jetkmail/__main__.py
jetkmail/login.py
jetkmail/tk.py
srml/__init__.py
srml/mailbox.py
srml/mime.hy
srml/msgbase.hy
srml/popclient.py
srml/rcml.py
srml/sdml.hy
jsrml-0.0.2.dist-info/METADATA
jsrml-0.0.2.dist-info/WHEEL
jsrml-0.0.2.dist-info/top_level.txt
jsrml-0.0.2.dist-info/RECORD
