Metadata-Version: 2.1
Name: jsrml
Version: 0.0.2
Summary: A module to send or recieve emails
Home-page: https://gituhb.com/jeefies/srml
Author: Jeef
Author-email: jeefy163@163.com
Maintainer: Jeef
Maintainer-email: jeefy163@163.com
License: UNKNOWN
Platform: UNKNOWN
Requires-Python: >=3.4
Requires-Dist: imapclient
